odoo/addons/cerrar_ventas_deposito_erroneas/Readme.md
odoo/addons/cerrar_ventas_deposito_erroneas/__init__.py
odoo/addons/cerrar_ventas_deposito_erroneas/__manifest__.py
odoo/addons/cerrar_ventas_deposito_erroneas/models/__init__.py
odoo/addons/cerrar_ventas_deposito_erroneas/models/ventas_deposito_erroneas.py
odoo/addons/cerrar_ventas_deposito_erroneas/views/ventas_dep_erroneas_boton_view.xml
odoo13_addon_cerrar_ventas_deposito_erroneas-13.0.0.0.1.dist-info/METADATA
odoo13_addon_cerrar_ventas_deposito_erroneas-13.0.0.0.1.dist-info/WHEEL
odoo13_addon_cerrar_ventas_deposito_erroneas-13.0.0.0.1.dist-info/top_level.txt
odoo13_addon_cerrar_ventas_deposito_erroneas-13.0.0.0.1.dist-info/RECORD
