Metadata-Version: 2.1
Name: odoo13-addon-cerrar_ventas_deposito_erroneas
Version: 13.0.0.0.1
Requires-Python: >=3.5
Requires-Dist: odoo>=13.0a,<13.1dev
Summary: =?utf-8?q?M=C3=B3dulo_Cerrar_ventas_a_dep=C3=B3sito_err=C3=B3neas_para_editoriales=2E?=
Home-page: https://framagit.org/devcontrol
License: OPL-1
Author: Colectivo DEVCONTROL
Classifier: Programming Language :: Python
Classifier: Framework :: Odoo
Classifier: Framework :: Odoo :: 13.0
